tdameritrade_cli/__init__.py
tdameritrade_cli/cli.py
tdameritrade_cli/tools/__init__.py
tdameritrade_cli/tools/client_factory.py
tdameritrade_cli/tools/ods_writer.py
tdameritrade_cli/tools/positions.py
tdameritrade_cli-0.2.1.dist-info/entry_points.txt
tdameritrade_cli-0.2.1.dist-info/LICENSE
tdameritrade_cli-0.2.1.dist-info/WHEEL
tdameritrade_cli-0.2.1.dist-info/METADATA
tdameritrade_cli-0.2.1.dist-info/RECORD
