Metadata-Version: 2.1
Name: tdameritrade-cli
Version: 0.2.1
Summary: A CLI built on top of the tdameritrade-client API library
Home-page: https://gitlab.com/tdameritrade-tools/tdameritrade-cli
Author: Joe Castagneri
Author-email: jcastagneri@gmail.com
Requires-Python: >=3.6,<4.0
Classifier: License :: OSI Approved :: MIT License
Classifier: Operating System :: MacOS
Classifier: Operating System :: Microsoft :: Windows
Classifier: Operating System :: POSIX :: Linux
Classifier: Programming Language :: Python :: 3
Classifier: Programming Language :: Python :: 3.6
Classifier: Programming Language :: Python :: 3.7
Requires-Dist: click (>=7.0,<8.0)
Requires-Dist: pyexcel-ods (>=0.5.6,<0.6.0)
Requires-Dist: tdameritrade-client (>=0.3,<0.4)
Project-URL: Documentation, https://tdameritrade-cli.readthedocs.io/en/latest/?#
Project-URL: Repository, https://gitlab.com/tdameritrade-tools/tdameritrade-cli
